odoo/addons/account_banking_reconciliation/README.rst
odoo/addons/account_banking_reconciliation/__init__.py
odoo/addons/account_banking_reconciliation/__manifest__.py
odoo/addons/account_banking_reconciliation/i18n/account_banking_reconciliation.pot
odoo/addons/account_banking_reconciliation/models/__init__.py
odoo/addons/account_banking_reconciliation/models/account_banking_reconciliation.py
odoo/addons/account_banking_reconciliation/models/account_move_line.py
odoo/addons/account_banking_reconciliation/readme/CONFIGURE.rst
odoo/addons/account_banking_reconciliation/readme/CONTRIBUTORS.rst
odoo/addons/account_banking_reconciliation/readme/CREDITS.rst
odoo/addons/account_banking_reconciliation/readme/DESCRIPTION.rst
odoo/addons/account_banking_reconciliation/readme/USAGE.rst
odoo/addons/account_banking_reconciliation/report/bank_statement_report.xml
odoo/addons/account_banking_reconciliation/report/report_bank_statement_detail.xml
odoo/addons/account_banking_reconciliation/report/report_bank_statement_summary.xml
odoo/addons/account_banking_reconciliation/security/account_banking_reconciliation.xml
odoo/addons/account_banking_reconciliation/security/ir.model.access.csv
odoo/addons/account_banking_reconciliation/static/description/icon.png
odoo/addons/account_banking_reconciliation/static/description/index.html
odoo/addons/account_banking_reconciliation/views/account_banking_reconciliation.xml
odoo/addons/account_banking_reconciliation/views/account_move_line.xml
odoo11_addon_account_banking_reconciliation-11.0.1.0.0.99.dev5.dist-info/METADATA
odoo11_addon_account_banking_reconciliation-11.0.1.0.0.99.dev5.dist-info/WHEEL
odoo11_addon_account_banking_reconciliation-11.0.1.0.0.99.dev5.dist-info/top_level.txt
odoo11_addon_account_banking_reconciliation-11.0.1.0.0.99.dev5.dist-info/RECORD
